<?xml version="1.0" encoding="UTF-8" standalone="yes"?>

<quiz>

<question type="category">
  <category>
    <text>Sekundar/03 EinheitenUmrechnen/Zeiten</text>
  </category>
  <info format="html">
    <text></text>
  </info>
  <idnumber></idnumber>
</question>

<question type="cloze">
  <name>
    <text>01 </text>
  </name>
  <questiontext format="html">
    <text><![CDATA[<p>Geben Sie die Größen in der gesuchten Einheit an.</p><ol><li value="1">84,7 h<br>{1:NUMERICAL:=3,5292:0} d</li></ol><ol><li value="2">1008 min<br>{1:NUMERICAL:=0,7:0} d</li></ol><ol><li value="3">25 h<br>{1:NUMERICAL:=1500:0} min</li></ol><ol><li value="4">112680 s<br>{1:NUMERICAL:=1878:0} min</li></ol><ol><li value="5">87,9 h<br>{1:NUMERICAL:=316440:0} s</li></ol>]]></text>
  </questiontext>
</question>

<question type="cloze">
  <name>
    <text>02 </text>
  </name>
  <questiontext format="html">
    <text><![CDATA[<p>Geben Sie die Größen in der gesuchten Einheit an.</p><ol><li value="1">4956 min<br>{1:NUMERICAL:=297360:0} s</li></ol><ol><li value="2">4962 min<br>{1:NUMERICAL:=82,7:0} h</li></ol><ol><li value="3">2,77083333333333 d<br>{1:NUMERICAL:=66,5:0} h</li></ol><ol><li value="4">1,30416666666667 d<br>{1:NUMERICAL:=1878:0} min</li></ol><ol><li value="5">82,8 h<br>{1:NUMERICAL:=3,45:0} d</li></ol>]]></text>
  </questiontext>
</question>

<question type="cloze">
  <name>
    <text>03 </text>
  </name>
  <questiontext format="html">
    <text><![CDATA[<p>Geben Sie die Größen in der gesuchten Einheit an.</p><ol><li value="1">86,3 h<br>{1:NUMERICAL:=3,5958:0} d</li></ol><ol><li value="2">89,9 h<br>{1:NUMERICAL:=323640:0} s</li></ol><ol><li value="3">0,3875 d<br>{1:NUMERICAL:=558:0} min</li></ol><ol><li value="4">195480 s<br>{1:NUMERICAL:=54,3:0} h</li></ol><ol><li value="5">1746 min<br>{1:NUMERICAL:=104760:0} s</li></ol>]]></text>
  </questiontext>
</question>

<question type="cloze">
  <name>
    <text>04 </text>
  </name>
  <questiontext format="html">
    <text><![CDATA[<p>Geben Sie die Größen in der gesuchten Einheit an.</p><ol><li value="1">190800 s<br>{1:NUMERICAL:=53:0} h</li></ol><ol><li value="2">93 h<br>{1:NUMERICAL:=5580:0} min</li></ol><ol><li value="3">1290 min<br>{1:NUMERICAL:=77400:0} s</li></ol><ol><li value="4">213840 s<br>{1:NUMERICAL:=3564:0} min</li></ol><ol><li value="5">69,5 h<br>{1:NUMERICAL:=2,8958:0} d</li></ol>]]></text>
  </questiontext>
</question>

<question type="cloze">
  <name>
    <text>05 </text>
  </name>
  <questiontext format="html">
    <text><![CDATA[<p>Geben Sie die Größen in der gesuchten Einheit an.</p><ol><li value="1">102 min<br>{1:NUMERICAL:=6120:0} s</li></ol><ol><li value="2">218160 s<br>{1:NUMERICAL:=60,6:0} h</li></ol><ol><li value="3">71,4 h<br>{1:NUMERICAL:=2,975:0} d</li></ol><ol><li value="4">2,92083333333333 d<br>{1:NUMERICAL:=70,1:0} h</li></ol><ol><li value="5">5982 min<br>{1:NUMERICAL:=4,1542:0} d</li></ol>]]></text>
  </questiontext>
</question>

<question type="cloze">
  <name>
    <text>06 </text>
  </name>
  <questiontext format="html">
    <text><![CDATA[<p>Geben Sie die Größen in der gesuchten Einheit an.</p><ol><li value="1">336600 s<br>{1:NUMERICAL:=93,5:0} h</li></ol><ol><li value="2">55,7 h<br>{1:NUMERICAL:=200520:0} s</li></ol><ol><li value="3">43,5 h<br>{1:NUMERICAL:=1,8125:0} d</li></ol><ol><li value="4">4536 min<br>{1:NUMERICAL:=272160:0} s</li></ol><ol><li value="5">36,6 h<br>{1:NUMERICAL:=2196:0} min</li></ol>]]></text>
  </questiontext>
</question>

<question type="cloze">
  <name>
    <text>07 </text>
  </name>
  <questiontext format="html">
    <text><![CDATA[<p>Geben Sie die Größen in der gesuchten Einheit an.</p><ol><li value="1">49,9 h<br>{1:NUMERICAL:=2,0792:0} d</li></ol><ol><li value="2">4752 min<br>{1:NUMERICAL:=285120:0} s</li></ol><ol><li value="3">780 min<br>{1:NUMERICAL:=0,5417:0} d</li></ol><ol><li value="4">5436 min<br>{1:NUMERICAL:=90,6:0} h</li></ol><ol><li value="5">322920 s<br>{1:NUMERICAL:=89,7:0} h</li></ol>]]></text>
  </questiontext>
</question>

<question type="cloze">
  <name>
    <text>08 </text>
  </name>
  <questiontext format="html">
    <text><![CDATA[<p>Geben Sie die Größen in der gesuchten Einheit an.</p><ol><li value="1">80,4 h<br>{1:NUMERICAL:=3,35:0} d</li></ol><ol><li value="2">1050 min<br>{1:NUMERICAL:=17,5:0} h</li></ol><ol><li value="3">2,18333333333333 d<br>{1:NUMERICAL:=52,4:0} h</li></ol><ol><li value="4">78,2 h<br>{1:NUMERICAL:=4692:0} min</li></ol><ol><li value="5">3 h<br>{1:NUMERICAL:=10800:0} s</li></ol>]]></text>
  </questiontext>
</question>

<question type="cloze">
  <name>
    <text>09 </text>
  </name>
  <questiontext format="html">
    <text><![CDATA[<p>Geben Sie die Größen in der gesuchten Einheit an.</p><ol><li value="1">3144 min<br>{1:NUMERICAL:=188640:0} s</li></ol><ol><li value="2">2,41666666666667 d<br>{1:NUMERICAL:=58:0} h</li></ol><ol><li value="3">1848 min<br>{1:NUMERICAL:=1,2833:0} d</li></ol><ol><li value="4">37,5 h<br>{1:NUMERICAL:=135000:0} s</li></ol><ol><li value="5">3654 min<br>{1:NUMERICAL:=60,9:0} h</li></ol>]]></text>
  </questiontext>
</question>

<question type="cloze">
  <name>
    <text>10 </text>
  </name>
  <questiontext format="html">
    <text><![CDATA[<p>Geben Sie die Größen in der gesuchten Einheit an.</p><ol><li value="1">4236 min<br>{1:NUMERICAL:=70,6:0} h</li></ol><ol><li value="2">60,5 h<br>{1:NUMERICAL:=2,5208:0} d</li></ol><ol><li value="3">2,925 d<br>{1:NUMERICAL:=4212:0} min</li></ol><ol><li value="4">1320 min<br>{1:NUMERICAL:=79200:0} s</li></ol><ol><li value="5">68,1 h<br>{1:NUMERICAL:=245160:0} s</li></ol>]]></text>
  </questiontext>
</question>

<question type="cloze">
  <name>
    <text>11 </text>
  </name>
  <questiontext format="html">
    <text><![CDATA[<p>Geben Sie die Größen in der gesuchten Einheit an.</p><ol><li value="1">3402 min<br>{1:NUMERICAL:=2,3625:0} d</li></ol><ol><li value="2">73 h<br>{1:NUMERICAL:=3,0417:0} d</li></ol><ol><li value="3">186840 s<br>{1:NUMERICAL:=3114:0} min</li></ol><ol><li value="4">25 h<br>{1:NUMERICAL:=1500:0} min</li></ol><ol><li value="5">95,6 h<br>{1:NUMERICAL:=344160:0} s</li></ol>]]></text>
  </questiontext>
</question>

<question type="cloze">
  <name>
    <text>12 </text>
  </name>
  <questiontext format="html">
    <text><![CDATA[<p>Geben Sie die Größen in der gesuchten Einheit an.</p><ol><li value="1">137160 s<br>{1:NUMERICAL:=2286:0} min</li></ol><ol><li value="2">2,875 d<br>{1:NUMERICAL:=4140:0} min</li></ol><ol><li value="3">36,8 h<br>{1:NUMERICAL:=1,5333:0} d</li></ol><ol><li value="4">71 h<br>{1:NUMERICAL:=255600:0} s</li></ol><ol><li value="5">5988 min<br>{1:NUMERICAL:=99,8:0} h</li></ol>]]></text>
  </questiontext>
</question>

<question type="cloze">
  <name>
    <text>13 </text>
  </name>
  <questiontext format="html">
    <text><![CDATA[<p>Geben Sie die Größen in der gesuchten Einheit an.</p><ol><li value="1">5928 min<br>{1:NUMERICAL:=355680:0} s</li></ol><ol><li value="2">5256 min<br>{1:NUMERICAL:=3,65:0} d</li></ol><ol><li value="3">34,9 h<br>{1:NUMERICAL:=125640:0} s</li></ol><ol><li value="4">46,7 h<br>{1:NUMERICAL:=1,9458:0} d</li></ol><ol><li value="5">248760 s<br>{1:NUMERICAL:=4146:0} min</li></ol>]]></text>
  </questiontext>
</question>

<question type="cloze">
  <name>
    <text>14 </text>
  </name>
  <questiontext format="html">
    <text><![CDATA[<p>Geben Sie die Größen in der gesuchten Einheit an.</p><ol><li value="1">18,9 h<br>{1:NUMERICAL:=1134:0} min</li></ol><ol><li value="2">61,2 h<br>{1:NUMERICAL:=2,55:0} d</li></ol><ol><li value="3">0,295833333333333 d<br>{1:NUMERICAL:=426:0} min</li></ol><ol><li value="4">250920 s<br>{1:NUMERICAL:=69,7:0} h</li></ol><ol><li value="5">1452 min<br>{1:NUMERICAL:=24,2:0} h</li></ol>]]></text>
  </questiontext>
</question>

<question type="cloze">
  <name>
    <text>15 </text>
  </name>
  <questiontext format="html">
    <text><![CDATA[<p>Geben Sie die Größen in der gesuchten Einheit an.</p><ol><li value="1">2,49166666666667 d<br>{1:NUMERICAL:=59,8:0} h</li></ol><ol><li value="2">98,5 h<br>{1:NUMERICAL:=5910:0} min</li></ol><ol><li value="3">3462 min<br>{1:NUMERICAL:=207720:0} s</li></ol><ol><li value="4">352800 s<br>{1:NUMERICAL:=5880:0} min</li></ol><ol><li value="5">3,85833333333333 d<br>{1:NUMERICAL:=5556:0} min</li></ol>]]></text>
  </questiontext>
</question>

<question type="cloze">
  <name>
    <text>16 </text>
  </name>
  <questiontext format="html">
    <text><![CDATA[<p>Geben Sie die Größen in der gesuchten Einheit an.</p><ol><li value="1">63 h<br>{1:NUMERICAL:=226800:0} s</li></ol><ol><li value="2">1638 min<br>{1:NUMERICAL:=1,1375:0} d</li></ol><ol><li value="3">2,15 d<br>{1:NUMERICAL:=3096:0} min</li></ol><ol><li value="4">95,8 h<br>{1:NUMERICAL:=3,9917:0} d</li></ol><ol><li value="5">300 min<br>{1:NUMERICAL:=5:0} h</li></ol>]]></text>
  </questiontext>
</question>

<question type="cloze">
  <name>
    <text>17 </text>
  </name>
  <questiontext format="html">
    <text><![CDATA[<p>Geben Sie die Größen in der gesuchten Einheit an.</p><ol><li value="1">46,7 h<br>{1:NUMERICAL:=1,9458:0} d</li></ol><ol><li value="2">290520 s<br>{1:NUMERICAL:=80,7:0} h</li></ol><ol><li value="3">21,4 h<br>{1:NUMERICAL:=77040:0} s</li></ol><ol><li value="4">3888 min<br>{1:NUMERICAL:=64,8:0} h</li></ol><ol><li value="5">2,36666666666667 d<br>{1:NUMERICAL:=56,8:0} h</li></ol>]]></text>
  </questiontext>
</question>

<question type="cloze">
  <name>
    <text>18 </text>
  </name>
  <questiontext format="html">
    <text><![CDATA[<p>Geben Sie die Größen in der gesuchten Einheit an.</p><ol><li value="1">190800 s<br>{1:NUMERICAL:=53:0} h</li></ol><ol><li value="2">93 h<br>{1:NUMERICAL:=5580:0} min</li></ol><ol><li value="3">1290 min<br>{1:NUMERICAL:=77400:0} s</li></ol><ol><li value="4">213840 s<br>{1:NUMERICAL:=3564:0} min</li></ol><ol><li value="5">69,5 h<br>{1:NUMERICAL:=2,8958:0} d</li></ol>]]></text>
  </questiontext>
</question>

<question type="cloze">
  <name>
    <text>19 </text>
  </name>
  <questiontext format="html">
    <text><![CDATA[<p>Geben Sie die Größen in der gesuchten Einheit an.</p><ol><li value="1">102 min<br>{1:NUMERICAL:=6120:0} s</li></ol><ol><li value="2">218160 s<br>{1:NUMERICAL:=60,6:0} h</li></ol><ol><li value="3">71,4 h<br>{1:NUMERICAL:=2,975:0} d</li></ol><ol><li value="4">2,92083333333333 d<br>{1:NUMERICAL:=70,1:0} h</li></ol><ol><li value="5">5982 min<br>{1:NUMERICAL:=4,1542:0} d</li></ol>]]></text>
  </questiontext>
</question>

<question type="cloze">
  <name>
    <text>20 </text>
  </name>
  <questiontext format="html">
    <text><![CDATA[<p>Geben Sie die Größen in der gesuchten Einheit an.</p><ol><li value="1">336600 s<br>{1:NUMERICAL:=93,5:0} h</li></ol><ol><li value="2">55,7 h<br>{1:NUMERICAL:=200520:0} s</li></ol><ol><li value="3">43,5 h<br>{1:NUMERICAL:=1,8125:0} d</li></ol><ol><li value="4">4536 min<br>{1:NUMERICAL:=272160:0} s</li></ol><ol><li value="5">36,6 h<br>{1:NUMERICAL:=2196:0} min</li></ol>]]></text>
  </questiontext>
</question>

</quiz>

