[
{
"einleitung":"Gegeben sind die Funktionen </p> <p>\\( f(x)=-6x \\)</p> <p> und </p> <p>\\( g(x)=8x+11,4 \\).",
"fragen":[
"Bestimmen Sie den Schnittpunkt der Funktionen \\( f \\) und \\( g \\)."
],
"antworten":[
"\\( P( \\){1:NUMERICAL:=-5,7:0}\\( | \\){1:NUMERICAL:=34,2:0}\\( ) \\)"
]
},
{
"einleitung":"Gegeben sind die Funktionen </p> <p>\\( f(x)=8x+1 \\)</p> <p> und </p> <p>\\( g(x)=-6x+10,6 \\).",
"fragen":[
"Bestimmen Sie den Schnittpunkt der Funktionen \\( f \\) und \\( g \\)."
],
"antworten":[
"\\( P( \\){1:NUMERICAL:=-5,8:0}\\( | \\){1:NUMERICAL:=-45,4:0}\\( ) \\)"
]
},
{
"einleitung":"Gegeben sind die Funktionen </p> <p>\\( f(x)=-3 \\)</p> <p> und </p> <p>\\( g(x)=4x+2,2 \\).",
"fragen":[
"Bestimmen Sie den Schnittpunkt der Funktionen \\( f \\) und \\( g \\)."
],
"antworten":[
"\\( P( \\){1:NUMERICAL:=0,2:0}\\( | \\){1:NUMERICAL:=-3:0}\\( ) \\)"
]
},
{
"einleitung":"Gegeben sind die Funktionen </p> <p>\\( f(x)=4x+6 \\)</p> <p> und </p> <p>\\( g(x)=-8x+19,2 \\).",
"fragen":[
"Bestimmen Sie den Schnittpunkt der Funktionen \\( f \\) und \\( g \\)."
],
"antworten":[
"\\( P( \\){1:NUMERICAL:=6,3:0}\\( | \\){1:NUMERICAL:=31,2:0}\\( ) \\)"
]
},
{
"einleitung":"Gegeben sind die Funktionen </p> <p>\\( f(x)=-3x \\)</p> <p> und </p> <p>\\( g(x)=-x-22,8 \\).",
"fragen":[
"Bestimmen Sie den Schnittpunkt der Funktionen \\( f \\) und \\( g \\)."
],
"antworten":[
"\\( P( \\){1:NUMERICAL:=-5,7:0}\\( | \\){1:NUMERICAL:=17,1:0}\\( ) \\)"
]
},
{
"einleitung":"Gegeben sind die Funktionen </p> <p>\\( f(x)=-4x-1 \\)</p> <p> und </p> <p>\\( g(x)=-4x+49,8 \\).",
"fragen":[
"Bestimmen Sie den Schnittpunkt der Funktionen \\( f \\) und \\( g \\)."
],
"antworten":[
"\\( P( \\){1:NUMERICAL:=6,1:0}\\( | \\){1:NUMERICAL:=-25,4:0}\\( ) \\)"
]
},
{
"einleitung":"Gegeben sind die Funktionen </p> <p>\\( f(x)=4 \\)</p> <p> und </p> <p>\\( g(x)=-9x+78,8 \\).",
"fragen":[
"Bestimmen Sie den Schnittpunkt der Funktionen \\( f \\) und \\( g \\)."
],
"antworten":[
"\\( P( \\){1:NUMERICAL:=9,2:0}\\( | \\){1:NUMERICAL:=4:0}\\( ) \\)"
]
},
{
"einleitung":"Gegeben sind die Funktionen </p> <p>\\( f(x)=-7 \\)</p> <p> und </p> <p>\\( g(x)=-6x+35,8 \\).",
"fragen":[
"Bestimmen Sie den Schnittpunkt der Funktionen \\( f \\) und \\( g \\)."
],
"antworten":[
"\\( P( \\){1:NUMERICAL:=4,8:0}\\( | \\){1:NUMERICAL:=-7:0}\\( ) \\)"
]
},
{
"einleitung":"Gegeben sind die Funktionen </p> <p>\\( f(x)=-3x-1 \\)</p> <p> und </p> <p>\\( g(x)=-4x-13,7 \\).",
"fragen":[
"Bestimmen Sie den Schnittpunkt der Funktionen \\( f \\) und \\( g \\)."
],
"antworten":[
"\\( P( \\){1:NUMERICAL:=-2,1:0}\\( | \\){1:NUMERICAL:=5,3:0}\\( ) \\)"
]
},
{
"einleitung":"Gegeben sind die Funktionen </p> <p>\\( f(x)=8x \\)</p> <p> und </p> <p>\\( g(x)=-2x-51 \\).",
"fragen":[
"Bestimmen Sie den Schnittpunkt der Funktionen \\( f \\) und \\( g \\)."
],
"antworten":[
"\\( P( \\){1:NUMERICAL:=8,5:0}\\( | \\){1:NUMERICAL:=68:0}\\( ) \\)"
]
},
{
"einleitung":"Gegeben sind die Funktionen </p> <p>\\( f(x)=-8x-5 \\)</p> <p> und </p> <p>\\( g(x)=6x+23,8 \\).",
"fragen":[
"Bestimmen Sie den Schnittpunkt der Funktionen \\( f \\) und \\( g \\)."
],
"antworten":[
"\\( P( \\){1:NUMERICAL:=9,4:0}\\( | \\){1:NUMERICAL:=-80,2:0}\\( ) \\)"
]
},
{
"einleitung":"Gegeben sind die Funktionen </p> <p>\\( f(x)=-4 \\)</p> <p> und </p> <p>\\( g(x)=-7x-42,2 \\).",
"fragen":[
"Bestimmen Sie den Schnittpunkt der Funktionen \\( f \\) und \\( g \\)."
],
"antworten":[
"\\( P( \\){1:NUMERICAL:=-6,6:0}\\( | \\){1:NUMERICAL:=-4:0}\\( ) \\)"
]
},
{
"einleitung":"Gegeben sind die Funktionen </p> <p>\\( f(x)= \\)</p> <p> und </p> <p>\\( g(x)=-6x-43,2 \\).",
"fragen":[
"Bestimmen Sie den Schnittpunkt der Funktionen \\( f \\) und \\( g \\)."
],
"antworten":[
"\\( P( \\){1:NUMERICAL:=-7,2:0}\\( | \\){1:NUMERICAL:=0:0}\\( ) \\)"
]
},
{
"einleitung":"Gegeben sind die Funktionen </p> <p>\\( f(x)= \\)</p> <p> und </p> <p>\\( g(x)=8x-77,6 \\).",
"fragen":[
"Bestimmen Sie den Schnittpunkt der Funktionen \\( f \\) und \\( g \\)."
],
"antworten":[
"\\( P( \\){1:NUMERICAL:=9,7:0}\\( | \\){1:NUMERICAL:=0:0}\\( ) \\)"
]
},
{
"einleitung":"Gegeben sind die Funktionen </p> <p>\\( f(x)= \\)</p> <p> und </p> <p>\\( g(x)=5x+33 \\).",
"fragen":[
"Bestimmen Sie den Schnittpunkt der Funktionen \\( f \\) und \\( g \\)."
],
"antworten":[
"\\( P( \\){1:NUMERICAL:=-6,6:0}\\( | \\){1:NUMERICAL:=0:0}\\( ) \\)"
]
},
{
"einleitung":"Gegeben sind die Funktionen </p> <p>\\( f(x)=2x \\)</p> <p> und </p> <p>\\( g(x)=-x-3,4 \\).",
"fragen":[
"Bestimmen Sie den Schnittpunkt der Funktionen \\( f \\) und \\( g \\)."
],
"antworten":[
"\\( P( \\){1:NUMERICAL:=3,4:0}\\( | \\){1:NUMERICAL:=6,8:0}\\( ) \\)"
]
},
{
"einleitung":"Gegeben sind die Funktionen </p> <p>\\( f(x)=8 \\)</p> <p> und </p> <p>\\( g(x)=-3x+3,7 \\).",
"fragen":[
"Bestimmen Sie den Schnittpunkt der Funktionen \\( f \\) und \\( g \\)."
],
"antworten":[
"\\( P( \\){1:NUMERICAL:=3,9:0}\\( | \\){1:NUMERICAL:=8:0}\\( ) \\)"
]
},
{
"einleitung":"Gegeben sind die Funktionen </p> <p>\\( f(x)= \\)</p> <p> und </p> <p>\\( g(x)=6x-11,4 \\).",
"fragen":[
"Bestimmen Sie den Schnittpunkt der Funktionen \\( f \\) und \\( g \\)."
],
"antworten":[
"\\( P( \\){1:NUMERICAL:=1,9:0}\\( | \\){1:NUMERICAL:=0:0}\\( ) \\)"
]
},
{
"einleitung":"Gegeben sind die Funktionen </p> <p>\\( f(x)=7 \\)</p> <p> und </p> <p>\\( g(x)=2x+1,8 \\).",
"fragen":[
"Bestimmen Sie den Schnittpunkt der Funktionen \\( f \\) und \\( g \\)."
],
"antworten":[
"\\( P( \\){1:NUMERICAL:=-4,4:0}\\( | \\){1:NUMERICAL:=7:0}\\( ) \\)"
]
},
{
"einleitung":"Gegeben sind die Funktionen </p> <p>\\( f(x)=-3x-4 \\)</p> <p> und </p> <p>\\( g(x)=x-11,8 \\).",
"fragen":[
"Bestimmen Sie den Schnittpunkt der Funktionen \\( f \\) und \\( g \\)."
],
"antworten":[
"\\( P( \\){1:NUMERICAL:=-7,9:0}\\( | \\){1:NUMERICAL:=19,7:0}\\( ) \\)"
]
}
]
