[
{
"einleitung":"Die Kostenfunktion eines Unternehmens lautet</p> <p>\\( K(x)=0,0013x^3-0,14x^2+5,9x+90 \\).</p> <p>Bestimmen Sie (auf 2 NKS gerundet)",
"fragen":[
"die kurzfristige Preisuntergrenze.",
"das Betriebsminimum.",
"die Menge beim Übergang vom degressiven zum progressiven Kostenwachstum."
],
"antworten":[
"{1:NUMERICAL:=2,1308:0,1}",
"{1:NUMERICAL:=53,8462:0,1}",
"{1:NUMERICAL:=35,8974:0,1}"
]
},
{
"einleitung":"Die Kostenfunktion eines Unternehmens lautet</p> <p>\\( K(x)=0,0031x^3-0,18x^2+3,7x+32 \\).</p> <p>Bestimmen Sie (auf 2 NKS gerundet)",
"fragen":[
"die kurzfristige Preisuntergrenze.",
"die Menge beim Übergang vom degressiven zum progressiven Kostenwachstum.",
"das Betriebsminimum."
],
"antworten":[
"{1:NUMERICAL:=1,0871:0,1}",
"{1:NUMERICAL:=19,3548:0,1}",
"{1:NUMERICAL:=29,0323:0,1}"
]
},
{
"einleitung":"Die Kostenfunktion eines Unternehmens lautet</p> <p>\\( K(x)=0,0012x^3-0,14x^2+6,1x+55 \\).</p> <p>Bestimmen Sie (auf 2 NKS gerundet)",
"fragen":[
"die Menge beim Übergang vom degressiven zum progressiven Kostenwachstum.",
"das Betriebsminimum.",
"die kurzfristige Preisuntergrenze."
],
"antworten":[
"{1:NUMERICAL:=38,8889:0,1}",
"{1:NUMERICAL:=58,3333:0,1}",
"{1:NUMERICAL:=2,0167:0,1}"
]
},
{
"einleitung":"Die Kostenfunktion eines Unternehmens lautet</p> <p>\\( K(x)=0,0028x^3-0,16x^2+3,9x+23 \\).</p> <p>Bestimmen Sie (auf 2 NKS gerundet)",
"fragen":[
"die kurzfristige Preisuntergrenze.",
"die Menge beim Übergang vom degressiven zum progressiven Kostenwachstum.",
"das Betriebsminimum."
],
"antworten":[
"{1:NUMERICAL:=1,6143:0,1}",
"{1:NUMERICAL:=19,0476:0,1}",
"{1:NUMERICAL:=28,5714:0,1}"
]
},
{
"einleitung":"Die Kostenfunktion eines Unternehmens lautet</p> <p>\\( K(x)=0,37x^3-4,2x^2+26x+28 \\).</p> <p>Bestimmen Sie (auf 2 NKS gerundet)",
"fragen":[
"die Menge beim Übergang vom degressiven zum progressiven Kostenwachstum.",
"die kurzfristige Preisuntergrenze.",
"das Betriebsminimum."
],
"antworten":[
"{1:NUMERICAL:=3,7838:0,1}",
"{1:NUMERICAL:=14,0811:0,1}",
"{1:NUMERICAL:=5,6757:0,1}"
]
},
{
"einleitung":"Die Kostenfunktion eines Unternehmens lautet</p> <p>\\( K(x)=0,0011x^3-0,1x^2+4,9x+60 \\).</p> <p>Bestimmen Sie (auf 2 NKS gerundet)",
"fragen":[
"das Betriebsminimum.",
"die kurzfristige Preisuntergrenze.",
"die Menge beim Übergang vom degressiven zum progressiven Kostenwachstum."
],
"antworten":[
"{1:NUMERICAL:=45,4545:0,1}",
"{1:NUMERICAL:=2,6273:0,1}",
"{1:NUMERICAL:=30,303:0,1}"
]
},
{
"einleitung":"Die Kostenfunktion eines Unternehmens lautet</p> <p>\\( K(x)=0,0044x^3-0,26x^2+5,2x+36 \\).</p> <p>Bestimmen Sie (auf 2 NKS gerundet)",
"fragen":[
"die Menge beim Übergang vom degressiven zum progressiven Kostenwachstum.",
"das Betriebsminimum.",
"die kurzfristige Preisuntergrenze."
],
"antworten":[
"{1:NUMERICAL:=19,697:0,1}",
"{1:NUMERICAL:=29,5455:0,1}",
"{1:NUMERICAL:=1,3591:0,1}"
]
},
{
"einleitung":"Die Kostenfunktion eines Unternehmens lautet</p> <p>\\( K(x)=1,1x^3-9,4x^2+69x+76 \\).</p> <p>Bestimmen Sie (auf 2 NKS gerundet)",
"fragen":[
"das Betriebsminimum.",
"die Menge beim Übergang vom degressiven zum progressiven Kostenwachstum.",
"die kurzfristige Preisuntergrenze."
],
"antworten":[
"{1:NUMERICAL:=4,2727:0,1}",
"{1:NUMERICAL:=2,8485:0,1}",
"{1:NUMERICAL:=48,9182:0,1}"
]
},
{
"einleitung":"Die Kostenfunktion eines Unternehmens lautet</p> <p>\\( K(x)=0,2x^3-2,3x^2+12x+18 \\).</p> <p>Bestimmen Sie (auf 2 NKS gerundet)",
"fragen":[
"die Menge beim Übergang vom degressiven zum progressiven Kostenwachstum.",
"die kurzfristige Preisuntergrenze.",
"das Betriebsminimum."
],
"antworten":[
"{1:NUMERICAL:=3,8333:0,1}",
"{1:NUMERICAL:=5,3875:0,1}",
"{1:NUMERICAL:=5,75:0,1}"
]
},
{
"einleitung":"Die Kostenfunktion eines Unternehmens lautet</p> <p>\\( K(x)=0,0037x^3-0,17x^2+4,5x+34 \\).</p> <p>Bestimmen Sie (auf 2 NKS gerundet)",
"fragen":[
"das Betriebsminimum.",
"die kurzfristige Preisuntergrenze.",
"die Menge beim Übergang vom degressiven zum progressiven Kostenwachstum."
],
"antworten":[
"{1:NUMERICAL:=22,973:0,1}",
"{1:NUMERICAL:=2,5473:0,1}",
"{1:NUMERICAL:=15,3153:0,1}"
]
},
{
"einleitung":"Die Kostenfunktion eines Unternehmens lautet</p> <p>\\( K(x)=0,059x^3-1,1x^2+14x+39 \\).</p> <p>Bestimmen Sie (auf 2 NKS gerundet)",
"fragen":[
"die kurzfristige Preisuntergrenze.",
"das Betriebsminimum.",
"die Menge beim Übergang vom degressiven zum progressiven Kostenwachstum."
],
"antworten":[
"{1:NUMERICAL:=8,8729:0,1}",
"{1:NUMERICAL:=9,322:0,1}",
"{1:NUMERICAL:=6,2147:0,1}"
]
},
{
"einleitung":"Die Kostenfunktion eines Unternehmens lautet</p> <p>\\( K(x)=0,46x^3-6x^2+28x+38 \\).</p> <p>Bestimmen Sie (auf 2 NKS gerundet)",
"fragen":[
"die kurzfristige Preisuntergrenze.",
"das Betriebsminimum.",
"die Menge beim Übergang vom degressiven zum progressiven Kostenwachstum."
],
"antworten":[
"{1:NUMERICAL:=8,4348:0,1}",
"{1:NUMERICAL:=6,5217:0,1}",
"{1:NUMERICAL:=4,3478:0,1}"
]
},
{
"einleitung":"Die Kostenfunktion eines Unternehmens lautet</p> <p>\\( K(x)=0,024x^3-0,46x^2+4,7x+16 \\).</p> <p>Bestimmen Sie (auf 2 NKS gerundet)",
"fragen":[
"das Betriebsminimum.",
"die Menge beim Übergang vom degressiven zum progressiven Kostenwachstum.",
"die kurzfristige Preisuntergrenze."
],
"antworten":[
"{1:NUMERICAL:=9,5833:0,1}",
"{1:NUMERICAL:=6,3889:0,1}",
"{1:NUMERICAL:=2,4958:0,1}"
]
},
{
"einleitung":"Die Kostenfunktion eines Unternehmens lautet</p> <p>\\( K(x)=0,0012x^3-0,12x^2+7x+85 \\).</p> <p>Bestimmen Sie (auf 2 NKS gerundet)",
"fragen":[
"die Menge beim Übergang vom degressiven zum progressiven Kostenwachstum.",
"das Betriebsminimum.",
"die kurzfristige Preisuntergrenze."
],
"antworten":[
"{1:NUMERICAL:=33,3333:0,1}",
"{1:NUMERICAL:=50:0,1}",
"{1:NUMERICAL:=4:0,1}"
]
},
{
"einleitung":"Die Kostenfunktion eines Unternehmens lautet</p> <p>\\( K(x)=0,13x^3-1,5x^2+6,8x+9,3 \\).</p> <p>Bestimmen Sie (auf 2 NKS gerundet)",
"fragen":[
"das Betriebsminimum.",
"die kurzfristige Preisuntergrenze.",
"die Menge beim Übergang vom degressiven zum progressiven Kostenwachstum."
],
"antworten":[
"{1:NUMERICAL:=5,7692:0,1}",
"{1:NUMERICAL:=2,4731:0,1}",
"{1:NUMERICAL:=3,8462:0,1}"
]
},
{
"einleitung":"Die Kostenfunktion eines Unternehmens lautet</p> <p>\\( K(x)=0,01x^3-0,44x^2+11x+75 \\).</p> <p>Bestimmen Sie (auf 2 NKS gerundet)",
"fragen":[
"die Menge beim Übergang vom degressiven zum progressiven Kostenwachstum.",
"die kurzfristige Preisuntergrenze.",
"das Betriebsminimum."
],
"antworten":[
"{1:NUMERICAL:=14,6667:0,1}",
"{1:NUMERICAL:=6,16:0,1}",
"{1:NUMERICAL:=22:0,1}"
]
},
{
"einleitung":"Die Kostenfunktion eines Unternehmens lautet</p> <p>\\( K(x)=0,0012x^3-0,13x^2+4,7x+91 \\).</p> <p>Bestimmen Sie (auf 2 NKS gerundet)",
"fragen":[
"das Betriebsminimum.",
"die Menge beim Übergang vom degressiven zum progressiven Kostenwachstum.",
"die kurzfristige Preisuntergrenze."
],
"antworten":[
"{1:NUMERICAL:=54,1667:0,1}",
"{1:NUMERICAL:=36,1111:0,1}",
"{1:NUMERICAL:=1,1792:0,1}"
]
},
{
"einleitung":"Die Kostenfunktion eines Unternehmens lautet</p> <p>\\( K(x)=0,19x^3-1,8x^2+11x+15 \\).</p> <p>Bestimmen Sie (auf 2 NKS gerundet)",
"fragen":[
"die Menge beim Übergang vom degressiven zum progressiven Kostenwachstum.",
"die kurzfristige Preisuntergrenze.",
"das Betriebsminimum."
],
"antworten":[
"{1:NUMERICAL:=3,1579:0,1}",
"{1:NUMERICAL:=6,7368:0,1}",
"{1:NUMERICAL:=4,7368:0,1}"
]
},
{
"einleitung":"Die Kostenfunktion eines Unternehmens lautet</p> <p>\\( K(x)=0,0079x^3-0,38x^2+7,8x+88 \\).</p> <p>Bestimmen Sie (auf 2 NKS gerundet)",
"fragen":[
"die kurzfristige Preisuntergrenze.",
"die Menge beim Übergang vom degressiven zum progressiven Kostenwachstum.",
"das Betriebsminimum."
],
"antworten":[
"{1:NUMERICAL:=3,2304:0,1}",
"{1:NUMERICAL:=16,0338:0,1}",
"{1:NUMERICAL:=24,0506:0,1}"
]
},
{
"einleitung":"Die Kostenfunktion eines Unternehmens lautet</p> <p>\\( K(x)=0,064x^3-1,4x^2+12x+32 \\).</p> <p>Bestimmen Sie (auf 2 NKS gerundet)",
"fragen":[
"die Menge beim Übergang vom degressiven zum progressiven Kostenwachstum.",
"das Betriebsminimum.",
"die kurzfristige Preisuntergrenze."
],
"antworten":[
"{1:NUMERICAL:=7,2917:0,1}",
"{1:NUMERICAL:=10,9375:0,1}",
"{1:NUMERICAL:=4,3438:0,1}"
]
}
]
