[
{
"einleitung":"Geben Sie die Längen  in der gesuchten Einheit an.",
"fragen":[
"Länge: 7,59 m",
"Länge: 2,5 m",
"Länge: 7980 mm",
"Länge: 52,4 dm",
"Länge: 9,19 m"
],
"antworten":[
"{1:NUMERICAL:=0,0076:0} km",
"{1:NUMERICAL:=25:0} dm",
"{1:NUMERICAL:=7,98:0} m",
"{1:NUMERICAL:=524:0} cm",
"{1:NUMERICAL:=9190:0} mm"
]
},
{
"einleitung":"Geben Sie die Längen  in der gesuchten Einheit an.",
"fragen":[
"Länge: 9,29 m",
"Länge: 86,5 dm",
"Länge: 765 cm",
"Länge: 0,00627 km",
"Länge: 0,00295 km"
],
"antworten":[
"{1:NUMERICAL:=9290:0} mm",
"{1:NUMERICAL:=865:0} cm",
"{1:NUMERICAL:=0,0077:0} km",
"{1:NUMERICAL:=627:0} cm",
"{1:NUMERICAL:=2,95:0} m"
]
},
{
"einleitung":"Geben Sie die Längen  in der gesuchten Einheit an.",
"fragen":[
"Länge: 0,00082 km",
"Länge: 9,71 m",
"Länge: 7,1 dm",
"Länge: 901 cm",
"Länge: 712 cm"
],
"antworten":[
"{1:NUMERICAL:=8,2:0} dm",
"{1:NUMERICAL:=97,1:0} dm",
"{1:NUMERICAL:=71:0} cm",
"{1:NUMERICAL:=9,01:0} m",
"{1:NUMERICAL:=71,2:0} dm"
]
},
{
"einleitung":"Geben Sie die Längen  in der gesuchten Einheit an.",
"fragen":[
"Länge: 0,00095 km",
"Länge: 76 cm",
"Länge: 266 cm",
"Länge: 0,00982 km",
"Länge: 9,08 m"
],
"antworten":[
"{1:NUMERICAL:=0,95:0} m",
"{1:NUMERICAL:=7,6:0} dm",
"{1:NUMERICAL:=2,66:0} m",
"{1:NUMERICAL:=982:0} cm",
"{1:NUMERICAL:=90,8:0} dm"
]
},
{
"einleitung":"Geben Sie die Längen  in der gesuchten Einheit an.",
"fragen":[
"Länge: 7,5 dm",
"Länge: 4,76 m",
"Länge: 7260 mm",
"Länge: 549 cm",
"Länge: 5500 mm"
],
"antworten":[
"{1:NUMERICAL:=750:0} mm",
"{1:NUMERICAL:=476:0} cm",
"{1:NUMERICAL:=726:0} cm",
"{1:NUMERICAL:=5,49:0} m",
"{1:NUMERICAL:=55:0} dm"
]
},
{
"einleitung":"Geben Sie die Längen  in der gesuchten Einheit an.",
"fragen":[
"Länge: 0,00883 km",
"Länge: 1980 mm",
"Länge: 557 cm",
"Länge: 76,2 dm",
"Länge: 73,1 dm"
],
"antworten":[
"{1:NUMERICAL:=883:0} cm",
"{1:NUMERICAL:=19,8:0} dm",
"{1:NUMERICAL:=55,7:0} dm",
"{1:NUMERICAL:=7620:0} mm",
"{1:NUMERICAL:=7,31:0} m"
]
},
{
"einleitung":"Geben Sie die Längen  in der gesuchten Einheit an.",
"fragen":[
"Länge: 397 cm",
"Länge: 34 cm",
"Länge: 1,09 m",
"Länge: 36,8 dm",
"Länge: 819 cm"
],
"antworten":[
"{1:NUMERICAL:=3,97:0} m",
"{1:NUMERICAL:=0,0003:0} km",
"{1:NUMERICAL:=109:0} cm",
"{1:NUMERICAL:=368:0} cm",
"{1:NUMERICAL:=8190:0} mm"
]
},
{
"einleitung":"Geben Sie die Längen  in der gesuchten Einheit an.",
"fragen":[
"Länge: 661 cm",
"Länge: 8670 mm",
"Länge: 53,6 dm",
"Länge: 0,0086 km",
"Länge: 329 cm"
],
"antworten":[
"{1:NUMERICAL:=6610:0} mm",
"{1:NUMERICAL:=8,67:0} m",
"{1:NUMERICAL:=5,36:0} m",
"{1:NUMERICAL:=8,6:0} m",
"{1:NUMERICAL:=32,9:0} dm"
]
},
{
"einleitung":"Geben Sie die Längen  in der gesuchten Einheit an.",
"fragen":[
"Länge: 36 cm",
"Länge: 0,00083 km",
"Länge: 93,6 dm",
"Länge: 3260 mm",
"Länge: 498 cm"
],
"antworten":[
"{1:NUMERICAL:=360:0} mm",
"{1:NUMERICAL:=0,83:0} m",
"{1:NUMERICAL:=9360:0} mm",
"{1:NUMERICAL:=3,26:0} m",
"{1:NUMERICAL:=49,8:0} dm"
]
},
{
"einleitung":"Geben Sie die Längen  in der gesuchten Einheit an.",
"fragen":[
"Länge: 0,00106 km",
"Länge: 627 cm",
"Länge: 0,00853 km",
"Länge: 49,4 dm",
"Länge: 0,00554 km"
],
"antworten":[
"{1:NUMERICAL:=106:0} cm",
"{1:NUMERICAL:=62,7:0} dm",
"{1:NUMERICAL:=8,53:0} m",
"{1:NUMERICAL:=4940:0} mm",
"{1:NUMERICAL:=55,4:0} dm"
]
},
{
"einleitung":"Geben Sie die Längen  in der gesuchten Einheit an.",
"fragen":[
"Länge: 3370 mm",
"Länge: 806 cm",
"Länge: 88,3 dm",
"Länge: 13,5 dm",
"Länge: 11,6 dm"
],
"antworten":[
"{1:NUMERICAL:=33,7:0} dm",
"{1:NUMERICAL:=0,0081:0} km",
"{1:NUMERICAL:=8830:0} mm",
"{1:NUMERICAL:=0,0014:0} km",
"{1:NUMERICAL:=1,16:0} m"
]
},
{
"einleitung":"Geben Sie die Längen  in der gesuchten Einheit an.",
"fragen":[
"Länge: 2500 mm",
"Länge: 0,1 m",
"Länge: 140 cm",
"Länge: 70,5 dm",
"Länge: 584 cm"
],
"antworten":[
"{1:NUMERICAL:=25:0} dm",
"{1:NUMERICAL:=1:0} dm",
"{1:NUMERICAL:=0,0014:0} km",
"{1:NUMERICAL:=7,05:0} m",
"{1:NUMERICAL:=5,84:0} m"
]
},
{
"einleitung":"Geben Sie die Längen  in der gesuchten Einheit an.",
"fragen":[
"Länge: 9,03 m",
"Länge: 616 cm",
"Länge: 6,8 m",
"Länge: 815 cm",
"Länge: 6200 mm"
],
"antworten":[
"{1:NUMERICAL:=9030:0} mm",
"{1:NUMERICAL:=61,6:0} dm",
"{1:NUMERICAL:=680:0} cm",
"{1:NUMERICAL:=0,0082:0} km",
"{1:NUMERICAL:=62:0} dm"
]
},
{
"einleitung":"Geben Sie die Längen  in der gesuchten Einheit an.",
"fragen":[
"Länge: 7,51 m",
"Länge: 0,28 m",
"Länge: 0,0064 km",
"Länge: 165 cm",
"Länge: 44,4 dm"
],
"antworten":[
"{1:NUMERICAL:=0,0075:0} km",
"{1:NUMERICAL:=2,8:0} dm",
"{1:NUMERICAL:=64:0} dm",
"{1:NUMERICAL:=1,65:0} m",
"{1:NUMERICAL:=4440:0} mm"
]
},
{
"einleitung":"Geben Sie die Längen  in der gesuchten Einheit an.",
"fragen":[
"Länge: 671 cm",
"Länge: 6,47 m",
"Länge: 7,03 m",
"Länge: 2 dm",
"Länge: 310 cm"
],
"antworten":[
"{1:NUMERICAL:=67,1:0} dm",
"{1:NUMERICAL:=647:0} cm",
"{1:NUMERICAL:=0,007:0} km",
"{1:NUMERICAL:=0,0002:0} km",
"{1:NUMERICAL:=3,1:0} m"
]
},
{
"einleitung":"Geben Sie die Längen  in der gesuchten Einheit an.",
"fragen":[
"Länge: 20,7 dm",
"Länge: 8270 mm",
"Länge: 493 cm",
"Länge: 5960 mm",
"Länge: 9,23 m"
],
"antworten":[
"{1:NUMERICAL:=2070:0} mm",
"{1:NUMERICAL:=82,7:0} dm",
"{1:NUMERICAL:=0,0049:0} km",
"{1:NUMERICAL:=596:0} cm",
"{1:NUMERICAL:=92,3:0} dm"
]
},
{
"einleitung":"Geben Sie die Längen  in der gesuchten Einheit an.",
"fragen":[
"Länge: 953 cm",
"Länge: 4,88 m",
"Länge: 0,2 dm",
"Länge: 0,00043 km",
"Länge: 3580 mm"
],
"antworten":[
"{1:NUMERICAL:=95,3:0} dm",
"{1:NUMERICAL:=0,0049:0} km",
"{1:NUMERICAL:=0,02:0} m",
"{1:NUMERICAL:=43:0} cm",
"{1:NUMERICAL:=3,58:0} m"
]
},
{
"einleitung":"Geben Sie die Längen  in der gesuchten Einheit an.",
"fragen":[
"Länge: 0,00052 km",
"Länge: 8610 mm",
"Länge: 5,7 dm",
"Länge: 784 cm",
"Länge: 103 cm"
],
"antworten":[
"{1:NUMERICAL:=52:0} cm",
"{1:NUMERICAL:=8,61:0} m",
"{1:NUMERICAL:=57:0} cm",
"{1:NUMERICAL:=0,0078:0} km",
"{1:NUMERICAL:=1030:0} mm"
]
},
{
"einleitung":"Geben Sie die Längen  in der gesuchten Einheit an.",
"fragen":[
"Länge: 0,00017 km",
"Länge: 0,9 dm",
"Länge: 8,02 m",
"Länge: 52 cm",
"Länge: 597 cm"
],
"antworten":[
"{1:NUMERICAL:=17:0} cm",
"{1:NUMERICAL:=90:0} mm",
"{1:NUMERICAL:=80,2:0} dm",
"{1:NUMERICAL:=0,52:0} m",
"{1:NUMERICAL:=0,006:0} km"
]
},
{
"einleitung":"Geben Sie die Längen  in der gesuchten Einheit an.",
"fragen":[
"Länge: 243 cm",
"Länge: 0,00129 km",
"Länge: 1,1 m",
"Länge: 9,38 m",
"Länge: 8 dm"
],
"antworten":[
"{1:NUMERICAL:=24,3:0} dm",
"{1:NUMERICAL:=129:0} cm",
"{1:NUMERICAL:=110:0} cm",
"{1:NUMERICAL:=93,8:0} dm",
"{1:NUMERICAL:=800:0} mm"
]
}
]
